grid_engine_Nitebound/grid_engine/__init__.py
grid_engine_Nitebound/grid_engine/core/__init__.py
grid_engine_Nitebound/grid_engine/core/camera.py
grid_engine_Nitebound/grid_engine/core/canvas.py
grid_engine_Nitebound/grid_engine/core/component.py
grid_engine_Nitebound/grid_engine/core/gameobject.py
grid_engine_Nitebound/grid_engine/core/scene.py
grid_engine_Nitebound/grid_engine/core/toolkit.py
grid_engine_Nitebound/grid_engine/features/__init__.py
grid_engine_Nitebound/grid_engine/features/components/__init__.py
grid_engine_Nitebound/grid_engine/features/components/mesh2d.py
grid_engine_Nitebound/grid_engine/features/components/rigidbody2d.py
grid_engine_Nitebound/grid_engine/features/components/transform.py
grid_engine_Nitebound/grid_engine/features/components/colliders/aabb_collider.py
grid_engine_Nitebound/grid_engine/features/components/colliders/circle_collider.py
grid_engine_Nitebound/grid_engine/features/components/colliders/collider.py
grid_engine_Nitebound/grid_engine/features/components/colliders/poly_collider.py
grid_engine_Nitebound/grid_engine/features/components/constraints/distance_constraint2d.py
grid_engine_Nitebound/grid_engine/features/components/networking/__init__.py
grid_engine_Nitebound/grid_engine/features/components/networking/worldclient.py
grid_engine_Nitebound/grid_engine/features/components/networking/worldserver.py
grid_engine_Nitebound/grid_engine/features/prefabs/Actor.py
grid_engine_Nitebound/grid_engine/features/prefabs/__init__.py
grid_engine_Nitebound/grid_engine/features/ui/__init__.py
grid_engine_Nitebound/grid_engine/features/ui/ui_button.py
grid_engine_Nitebound/grid_engine/features/ui/ui_element.py
grid_engine_Nitebound/grid_engine/features/ui/ui_manager.py
grid_engine_Nitebound/grid_engine/features/ui/ui_panel.py
grid_engine_Nitebound/grid_engine/features/ui/ui_stacklayout.py
grid_engine_Nitebound/grid_engine/features/ui/ui_style.py
grid_engine_Nitebound/grid_engine/features/ui/ui_surface.py
grid_engine_Nitebound-0.0.2.dist-info/LICENSE
grid_engine_Nitebound-0.0.2.dist-info/METADATA
grid_engine_Nitebound-0.0.2.dist-info/WHEEL
grid_engine_Nitebound-0.0.2.dist-info/top_level.txt
grid_engine_Nitebound-0.0.2.dist-info/RECORD
