Metadata-Version: 2.1
Name: grid_engine_Nitebound
Version: 0.0.2
Summary: The Nitegame Grid Engine
Author-email: NiteboundX <niteboundx@gmail.com>
License: MIT License
Project-URL: Homepage, https://github.com/NiteboundX/grid_engine_Nitebound
Project-URL: Issues, https://github.com/NiteboundX/grid_engine_Nitebound/issues
Classifier: Development Status :: 2 - Pre-Alpha
Classifier: Intended Audience :: Developers
Classifier: License :: OSI Approved :: MIT License
Classifier: Programming Language :: Python :: 3
Classifier: Programming Language :: Python :: 3.8
Classifier: Programming Language :: Python :: 3.9
Classifier: Programming Language :: Python :: 3.10
Classifier: Programming Language :: Python :: 3.11
Classifier: Operating System :: OS Independent
Classifier: Topic :: Software Development :: Libraries
Classifier: Topic :: Games/Entertainment
Requires-Python: >=3.8
License-File: LICENSE
Requires-Dist: pygame >=2.0.0
Requires-Dist: numpy >=1.18.0
Requires-Dist: PyOpenGL >=3.1.5
Requires-Dist: PyOpenGL-accelerate >=3.1.5
